{"paths":{"0":["attacktoxic",0],"1":["stickattack",0],"2":["tvwhite",0],"3":["cashiering",0],"4":["oilgold",0],"5":["shuriken",0],"6":["mutant",0],"7":["cat",0],"8":["punch2",0],"9":["levelup",0],"10":["zombiefall",0],"11":["attackelectric",0],"12":["attackice",0],"13":["bgm002",0],"14":["coin",0],"15":["skillmagicball",0],"16":["playerhit",0],"17":["meleereflectwall",0],"18":["pickup",0],"19":["bleeding",0],"20":["jump",0],"21":["melee",0],"22":["attackfire",0],"23":["fist1",0],"24":["meleereflect",0],"25":["shoot003",0],"26":["trash",0],"27":["bossicedemonthron",0],"28":["bossicedemonhit",0],"29":["shoot001",0],"30":["walk",0],"31":["monsterhit",0],"32":["swordattack1",0],"33":["jumpwater",0],"34":["boom",0],"35":["zombiespitting1",0],"36":["meleeparry",0],"37":["waterdispenser",0],"38":["bubble",0],"39":["dagger1",0],"40":["chicken",0],"41":["takephoto",0],"42":["swordattack2",0],"43":["meleereflectwood1",0],"44":["stickattack2",0],"45":["shoot",0],"46":["bgm001",0],"47":["iceboom",0],"48":["coin1",0],"49":["swordhit1",0],"50":["scarabcrawl",0],"51":["coin2",0],"52":["dolldown",0],"53":["punch",0],"54":["stickattack3",0],"55":["zombieattack",0],"56":["meleereflectwall1",0],"57":["pickitem",0],"58":["silence",0],"59":["dollmachine",0],"60":["complete",0],"61":["meleereflectwood3",0],"62":["meleereflectwood2",0],"63":["exit",0],"64":["dagger2",0],"65":["wentlineshow",0],"66":["raindrop",0],"67":["attackcurse",0],"68":["bossicedemondefend",0],"69":["fireball",0],"70":["bossicedemondash",0],"71":["bossicedemonattack",0],"72":["bathing",0],"73":["flashlight",0],"74":["tvcolor",0],"75":["strikeiron1",0],"76":["skillfireball",0],"77":["shoot004",0],"78":["feedfish",0],"79":["jumpfall",0],"80":["senbon",0],"81":["skillmagicball1",0],"82":["skillicethron",0],"83":["dash",0],"84":["swordhit2",0],"85":["drink",0],"86":["dagger",0],"87":["swordattack",0],"88":["meleereflect1",0],"89":["dog",0],"90":["blink",0],"91":["laser",0],"92":["swordshow",0],"93":["smokeball",0],"94":["wentlineopen",0],"95":["attackbleeding",0],"96":["swordhit",0],"97":["fist2",0],"98":["shoot002",0],"99":["fishtank",0],"100":["openchest",0],"101":["closestool",0],"102":["fist",0],"103":["monsterhit2",0],"104":["dash1",0],"105":["strikeiron",0],"106":["reload",0],"107":["mouse",0],"108":["stickattack1",0],"109":["waterfall",0],"110":["voice",0],"111":["swimming",0],"112":["welcome",0],"113":["zombiespitting",0],"114":["monsterhit1",0],"115":["punch1",0],"116":["die",0]},"types":["cc.AudioClip"],"uuids":["00hTzPc99Hs6faDZqDOVoS","02b4iOAsdH3q9HH1OJlPe/","02pfjgCDZEZ5pDk0hdmxPR","03TBy8GOZIrLqNCjQmxLja","052Gz0xSFBDoFSa9LGqhNa","06UmVgZ5NP1qXVGyNkQ9aa","0a+iP/1h9IBocgcAmNekVC","0bO2KFOSFEspXjn6aGTxw+","0eLkbhSx5Gs6ZFoI7BgfNG","10V/oI8FdBAK3tC9H+zy7l","10l4BDlDJD0YhWVarcVHhz","11OXuM469C9Y5y0e7YbKbO","11RZ3u3z1KCL/Gh1jbjCh6","12DD3N1G5BKoZrLozsSgiG","12NoBAa5ZACazJq14BBe1U","14PT9udylMX5ES6n4ABrOn","17nNwnNl5OpYBOO/JF2vu9","2417xpcM5OSYcM6l0SXeJt","25QjGitjpJDbPkLmjAgdqf","2fu/aLZ+dBL41YcfT544ts","30nHZ+L2tGCK1H2cCz/6d4","34PLa1cJ1KV6M/LJgUHAhN","34h+lhRttHC7s3a4B1Vs6G","349fSVmZNMdKxcZapHKe/c","38quSzUWZNtL6MfxCMAotP","3cRykfX9dFGpk33le7YPgb","3cz2Ptc6hNQZ6juHKIuGbk","3eSHyW+GpPaK/GAq6XWZCJ","44P3X/RkFPpJGDNjra0O9A","4alWr5LH5E5qGX645oUXG1","4fkVfbOuRAP5WT/NlBqkMU","51NZUfzNRAzJMOhMqQDQGJ","51aq3hWj1EVbDI+S/j8msS","57joD4q+tCO4ffqCZm5TPb","58LGFIg2dPrJlKEkLFSeI0","590iJ4XQZDdqDGlx5iZehG","599yUJhOhEIZXe+2aeC8G2","5dCHYy94xJOLuticrbqBzU","5dwp7/5ohNzZyY6bAKB5sC","60Uh14b4xB4qiCk6/CNbWO","617KDjBzVJCYAs0NNUyUUQ","637a4bv1BGzI9a+DoQ6Cog","652C2jxA9DX47XKpkunZ8h","68lRTTJ/9BLoKncm30xjNz","6cVJQGhWZGVp+Q6HfVLN+w","6e0hLNXNNA5rvcx39Iszzh","6f5r/RvaZBDL5tkpSgLjBT","709Aj6D3RCKqAN3oLFz/Q3","73PjoRTL5PeonH5JjHlCHG","73xSFU9rdIq6BLG5XZZCtW","75pkWxJIlDe7bbSKy/eEH7","77T92eEI9Mo7ScUiXiaSCg","78bMHAeJJJ9Jir5Ypcd+i7","78dtCEB41CHJTZAakxmtGv","79lOi9Yc5BfKpDf19IjDSr","80YDaw81lHpqDclIvCxnzT","83yRv+tONMCYCm9+b+DF+D","88uaNydf9IUaLcEiNc1AR5","8acb5GmQ9DXYORyDsDSriM","8afvjGX21FNpiNBLHQLwp2","8bBUwnrytCdJTsycL1njlE","8cAJVR2o1H5a0WfQgChlQS","8cFtwrpwNJ+6lnAzE4iA8B","8e66gCh3BEC6YdxZW5AEII","91QNgKEYlARIsI8iw2OCQH","92U6nUAxJHH7Ir1rqOZi5e","92ZdyPRY9F2LB3PUdN1lJW","92apXX/GRIW4EvMvbQ30E5","92qRggaGpBy7VLiLAJc17X","93ZBBDxI9Gl7XO5DGWV6og","93nrar/DRFF7v4HzfjqQb9","947X1KJOFMoq11r4ucLVSa","95kzHyDQpIEbxr9gxzDVdt","964GSn8zBF0LYxAFt/hTdY","97RdMK2YFIopkW/yCQO/o+","98vqu62ZRDxKxSOdAVx7E9","9a5cC9hARIbalwR4r+9CTq","9bExsVLCNKHpt6P+HusdOt","9c0FlLhCJFoKKttt/Fobls","a0uvzj0YhKK6lhWTO1FwKO","a12iK9BzlA8rHNN5KpZX97","a2C9CdH7pC5bexMULkG34r","a2dlRRUHxHnYRjgfhMmIZ7","a79UhxjphGE41DDZRNeHZ1","a8hR3gtd9IzZmoTKc9HUWA","a8zXfeMxhNzJ4oRV+aKjJe","ad2guwK4JAL5MmfjoUNxYr","aeV+4pwKdHaaIoqF9VYNtZ","afTvoiQb9DS5OBEvLqzMta","b0hJw+Q2dNB6FVWuFuynrZ","b4JVBgiSxDe4psxVPVl59+","b4k3VAdeBGWqDTQGkFPkhW","b6eAsAq8VL2oqzwvxdwYJb","b9FgdljWlGy7PpVgcvgTDO","bcPbHK1S1Fy7/ikq8llu8Q","c2V3DyMqxDIq9m1gtClz+D","c5vqBCGNREN63EJDhfGKZk","c6q/FVSrRIAbfmSRRZA1Nd","c6sz66iuNOqYMyCqsZylKF","caCin2PzVLnLLbhVS7qvKW","ceQkFwxdlJ7qSiWZ6ihY/W","d4PRCWzj1CepzHMAiuzoaX","d5hhe8Pf9JfKzF3mQC0w9D","ddLMfHwvxN0YwsVvNQzBhZ","df13LaOpxO3b3/G2xwOb1n","e7wGmwbadEt5WN3FmucVqb","e8PL1/w6RKEr/Hymx5oO5z","earaDbUnxK9oUgwSOoo4GM","ecc2AJdwdOmYuuZX4mPkmb","eefcOlnDhPsKJmfbHdVgfx","f0X6VgOLlLNZYT2G61J8Zi","f5+SO+UShIg65rwTXZFhIL","f6oZ1oYHNN0JqVID1u92jR","f6yhxWKq9PXpodtg1GtmJQ","fa4Bc8Qq1JQry2qetebBg9","fbr6wQsP1D2axiQtzxt9Ha","feBIl9EuBCn7nTVOq0MaO+"],"scenes":{},"redirect":[],"deps":[],"packs":{},"name":"ab_sound","importBase":"import","nativeBase":"native","debug":false,"isZip":false,"encrypted":false,"versions":{"import":[0,"48864",1,"7413a",2,"8928d",3,"442ed",4,"be9f3",5,"cb8e6",6,"134f1",7,"eb276",8,"87f81",9,"abc38",10,"09217",11,"4dc51",12,"6f46c",13,"64c86",14,"1c624",15,"d4b5a",16,"4d564",17,"d2364",18,"92630",19,"05f25",20,"da2fc",21,"a216a",22,"07cdd",23,"1edbf",24,"0dbbd",25,"634ca",26,"73123",27,"9873e",28,"c5743",29,"d202c",30,"d035f",31,"ff581",32,"51e4c",33,"5fd64",34,"06558",35,"1c7a2",36,"57029",37,"2a2d9",38,"a39ee",39,"b813f",40,"e9cae",41,"bf7f2",42,"bb3a6",43,"5fe1e",44,"38f89",45,"b907f",46,"822dc",47,"607b2",48,"38557",49,"62068",50,"a65db",51,"932b2",52,"38eeb",53,"26cdd",54,"c9e5b",55,"4b0fd",56,"82a2b",57,"a1102",58,"d9288",59,"21688",60,"04d89",61,"110f0",62,"2fffa",63,"2816f",64,"2e68f",65,"26033",66,"5a0f8",67,"6287d",68,"36c10",69,"8c04f",70,"a49cb",71,"1e641",72,"db63d",73,"0f8ad",74,"d0ff5",75,"25316",76,"f745a",77,"cc5d4",78,"de083",79,"688cb",80,"a1263",81,"649aa",82,"a7a8b",83,"9fd5a",84,"f452d",85,"26043",86,"3fe70",87,"19225",88,"9a63e",89,"fc0b0",90,"a3828",91,"84be7",92,"3178d",93,"996b7",94,"d2c5b",95,"a3593",96,"0d813",97,"f690c",98,"e4329",99,"41c8e",100,"6ce54",101,"d8278",102,"912dc",103,"286dc",104,"5e4b6",105,"bc218",106,"7197e",107,"5b1aa",108,"1822b",109,"737d5",110,"ee816",111,"f015e",112,"88be9",113,"9afda",114,"76913",115,"b3cfb",116,"768d4"],"native":[0,"26ad2",1,"eda36",2,"98b96",3,"1faa6",4,"5fc74",5,"56306",6,"86af8",7,"c3847",8,"7f5da",9,"6012b",10,"6e76f",11,"d477c",12,"34055",13,"fea6c",14,"e1454",15,"cf579",16,"2d8d3",17,"cc6e7",18,"c2233",19,"7bebf",20,"82f4b",21,"78861",22,"94606",23,"67b80",24,"c2611",25,"98f7e",26,"0045f",27,"f2a54",28,"3364d",29,"f56cb",30,"8e226",31,"f7e39",32,"9e98c",33,"642ad",34,"f3d6d",35,"ac98c",36,"10fd0",37,"d8b23",38,"68505",39,"e1bb4",40,"124d8",41,"7b485",42,"e596c",43,"e41e5",44,"503b1",45,"cc9ae",46,"8d352",47,"c5634",48,"54043",49,"055fd",50,"ecda4",51,"834fa",52,"92c8e",53,"e146b",54,"1c9b5",55,"623c3",56,"55f53",57,"8679a",58,"1a80c",59,"1b66c",60,"49f14",61,"87e9e",62,"0b524",63,"4d7e6",64,"21339",65,"15c31",66,"928f6",67,"199af",68,"76c9a",69,"94606",70,"2b6bb",71,"3a4c7",72,"364a1",73,"11e45",74,"569bb",75,"87530",76,"7f3f3",77,"316ef",78,"9a3e4",79,"ee53d",80,"c09a4",81,"1bb2b",82,"ef2d0",83,"64463",84,"9b9ca",85,"35178",86,"b3ad0",87,"60faa",88,"87534",89,"2160b",90,"1ae98",91,"db6fd",92,"4f8c7",93,"2ebb6",94,"f2322",95,"7bebf",96,"218ab",97,"f185d",98,"2723c",99,"24160",100,"48593",101,"0f69d",102,"f16c6",103,"9bf1a",104,"8f0e1",105,"7d87f",106,"313d0",107,"bc03e",108,"b68ca",109,"6a812",110,"9623f",111,"aad47",112,"be90f",113,"a2ed0",114,"e4295",115,"bbd73",116,"db18c"]}}