[1,["23iWbCFZdG/o2IjQfNjR+c"],["_textureSetter"],["cc.SpriteFrame"],0,[[[{"name":"waterdispenser3","rect":[281,326,11,28],"offset":[-0.5,2],"originalSize":[32,32],"capInsets":[0,0,0,0]}],[0],0,[0],[0],[0]],[[{"name":"waterdispenser1","rect":[478,189,11,28],"offset":[-0.5,2],"originalSize":[32,32],"capInsets":[0,0,0,0]}],[0],0,[0],[0],[0]],[[{"name":"waterdispenser2","rect":[478,219,11,28],"offset":[-0.5,2],"originalSize":[32,32],"capInsets":[0,0,0,0]}],[0],0,[0],[0],[0]],[[{"name":"cups01","rect":[825,243,3,4],"offset":[0,-0.5],"originalSize":[5,7],"capInsets":[0,0,0,0]}],[0],0,[0],[0],[0]],[[{"name":"waterdispenser0","rect":[281,296,11,28],"offset":[-0.5,2],"originalSize":[32,32],"capInsets":[0,0,0,0]}],[0],0,[0],[0],[0]]]]